{
  "version": "5",
  "dialect": "mysql",
  "id": "d4e1f29b-1756-4e61-bf6e-cb5769acf5fe",
  "prevId": "00000000-0000-0000-0000-000000000000",
  "tables": {
    "materials": {
      "name": "materials",
      "columns": {
        "id": {
          "name": "id",
          "type": "int",
          "primaryKey": false,
          "notNull": true,
          "autoincrement": true
        },
        "name": {
          "name": "name",
          "type": "varchar(255)",
          "primaryKey": false,
          "notNull": true,
          "autoincrement": false
        },
        "unit": {
          "name": "unit",
          "type": "varchar(50)",
          "primaryKey": false,
          "notNull": true,
          "autoincrement": false
        },
        "description": {
          "name": "description",
          "type": "text",
          "primaryKey": false,
          "notNull": false,
          "autoincrement": false
        }
      },
      "indexes": {},
      "foreignKeys": {},
      "compositePrimaryKeys": {
        "materials_id": {
          "name": "materials_id",
          "columns": [
            "id"
          ]
        }
      },
      "uniqueConstraints": {},
      "checkConstraint": {}
    },
    "notifications": {
      "name": "notifications",
      "columns": {
        "id": {
          "name": "id",
          "type": "int",
          "primaryKey": false,
          "notNull": true,
          "autoincrement": true
        },
        "sender_id": {
          "name": "sender_id",
          "type": "int",
          "primaryKey": false,
          "notNull": true,
          "autoincrement": false
        },
        "recipient_role": {
          "name": "recipient_role",
          "type": "enum('ADMIN_UP3','ADMIN_ULP')",
          "primaryKey": false,
          "notNull": false,
          "autoincrement": false
        },
        "recipient_ulp_id": {
          "name": "recipient_ulp_id",
          "type": "int",
          "primaryKey": false,
          "notNull": false,
          "autoincrement": false
        },
        "message": {
          "name": "message",
          "type": "text",
          "primaryKey": false,
          "notNull": true,
          "autoincrement": false
        },
        "is_read": {
          "name": "is_read",
          "type": "boolean",
          "primaryKey": false,
          "notNull": true,
          "autoincrement": false,
          "default": false
        },
        "created_at": {
          "name": "created_at",
          "type": "timestamp",
          "primaryKey": false,
          "notNull": true,
          "autoincrement": false,
          "default": "(now())"
        }
      },
      "indexes": {},
      "foreignKeys": {
        "notifications_sender_id_users_id_fk": {
          "name": "notifications_sender_id_users_id_fk",
          "tableFrom": "notifications",
          "tableTo": "users",
          "columnsFrom": [
            "sender_id"
          ],
          "columnsTo": [
            "id"
          ],
          "onDelete": "no action",
          "onUpdate": "no action"
        },
        "notifications_recipient_ulp_id_ulps_id_fk": {
          "name": "notifications_recipient_ulp_id_ulps_id_fk",
          "tableFrom": "notifications",
          "tableTo": "ulps",
          "columnsFrom": [
            "recipient_ulp_id"
          ],
          "columnsTo": [
            "id"
          ],
          "onDelete": "no action",
          "onUpdate": "no action"
        }
      },
      "compositePrimaryKeys": {
        "notifications_id": {
          "name": "notifications_id",
          "columns": [
            "id"
          ]
        }
      },
      "uniqueConstraints": {},
      "checkConstraint": {}
    },
    "stocks": {
      "name": "stocks",
      "columns": {
        "id": {
          "name": "id",
          "type": "int",
          "primaryKey": false,
          "notNull": true,
          "autoincrement": true
        },
        "material_id": {
          "name": "material_id",
          "type": "int",
          "primaryKey": false,
          "notNull": true,
          "autoincrement": false
        },
        "ulp_id": {
          "name": "ulp_id",
          "type": "int",
          "primaryKey": false,
          "notNull": false,
          "autoincrement": false
        },
        "quantity": {
          "name": "quantity",
          "type": "int",
          "primaryKey": false,
          "notNull": true,
          "autoincrement": false,
          "default": 0
        }
      },
      "indexes": {},
      "foreignKeys": {
        "stocks_material_id_materials_id_fk": {
          "name": "stocks_material_id_materials_id_fk",
          "tableFrom": "stocks",
          "tableTo": "materials",
          "columnsFrom": [
            "material_id"
          ],
          "columnsTo": [
            "id"
          ],
          "onDelete": "no action",
          "onUpdate": "no action"
        },
        "stocks_ulp_id_ulps_id_fk": {
          "name": "stocks_ulp_id_ulps_id_fk",
          "tableFrom": "stocks",
          "tableTo": "ulps",
          "columnsFrom": [
            "ulp_id"
          ],
          "columnsTo": [
            "id"
          ],
          "onDelete": "no action",
          "onUpdate": "no action"
        }
      },
      "compositePrimaryKeys": {
        "stocks_id": {
          "name": "stocks_id",
          "columns": [
            "id"
          ]
        }
      },
      "uniqueConstraints": {},
      "checkConstraint": {}
    },
    "transaction_details": {
      "name": "transaction_details",
      "columns": {
        "id": {
          "name": "id",
          "type": "int",
          "primaryKey": false,
          "notNull": true,
          "autoincrement": true
        },
        "transaction_id": {
          "name": "transaction_id",
          "type": "int",
          "primaryKey": false,
          "notNull": true,
          "autoincrement": false
        },
        "material_id": {
          "name": "material_id",
          "type": "int",
          "primaryKey": false,
          "notNull": true,
          "autoincrement": false
        },
        "quantity": {
          "name": "quantity",
          "type": "int",
          "primaryKey": false,
          "notNull": true,
          "autoincrement": false
        },
        "description": {
          "name": "description",
          "type": "text",
          "primaryKey": false,
          "notNull": false,
          "autoincrement": false
        }
      },
      "indexes": {},
      "foreignKeys": {
        "transaction_details_transaction_id_transactions_id_fk": {
          "name": "transaction_details_transaction_id_transactions_id_fk",
          "tableFrom": "transaction_details",
          "tableTo": "transactions",
          "columnsFrom": [
            "transaction_id"
          ],
          "columnsTo": [
            "id"
          ],
          "onDelete": "no action",
          "onUpdate": "no action"
        },
        "transaction_details_material_id_materials_id_fk": {
          "name": "transaction_details_material_id_materials_id_fk",
          "tableFrom": "transaction_details",
          "tableTo": "materials",
          "columnsFrom": [
            "material_id"
          ],
          "columnsTo": [
            "id"
          ],
          "onDelete": "no action",
          "onUpdate": "no action"
        }
      },
      "compositePrimaryKeys": {
        "transaction_details_id": {
          "name": "transaction_details_id",
          "columns": [
            "id"
          ]
        }
      },
      "uniqueConstraints": {},
      "checkConstraint": {}
    },
    "transactions": {
      "name": "transactions",
      "columns": {
        "id": {
          "name": "id",
          "type": "int",
          "primaryKey": false,
          "notNull": true,
          "autoincrement": true
        },
        "reference_number": {
          "name": "reference_number",
          "type": "varchar(100)",
          "primaryKey": false,
          "notNull": true,
          "autoincrement": false
        },
        "type": {
          "name": "type",
          "type": "enum('DISTRIBUTION','USAGE','INCOMING')",
          "primaryKey": false,
          "notNull": true,
          "autoincrement": false
        },
        "status": {
          "name": "status",
          "type": "enum('REQUESTED','DRAFT','APPROVED_ULP','COMPLETED')",
          "primaryKey": false,
          "notNull": true,
          "autoincrement": false,
          "default": "'DRAFT'"
        },
        "created_by": {
          "name": "created_by",
          "type": "int",
          "primaryKey": false,
          "notNull": true,
          "autoincrement": false
        },
        "target_ulp_id": {
          "name": "target_ulp_id",
          "type": "int",
          "primaryKey": false,
          "notNull": false,
          "autoincrement": false
        },
        "created_at": {
          "name": "created_at",
          "type": "timestamp",
          "primaryKey": false,
          "notNull": true,
          "autoincrement": false,
          "default": "(now())"
        },
        "approved_at": {
          "name": "approved_at",
          "type": "datetime",
          "primaryKey": false,
          "notNull": false,
          "autoincrement": false
        },
        "taker_name": {
          "name": "taker_name",
          "type": "varchar(255)",
          "primaryKey": false,
          "notNull": false,
          "autoincrement": false
        },
        "usage_purpose": {
          "name": "usage_purpose",
          "type": "varchar(255)",
          "primaryKey": false,
          "notNull": false,
          "autoincrement": false
        },
        "request_letter_base64": {
          "name": "request_letter_base64",
          "type": "text",
          "primaryKey": false,
          "notNull": false,
          "autoincrement": false
        },
        "photo_base64": {
          "name": "photo_base64",
          "type": "text",
          "primaryKey": false,
          "notNull": false,
          "autoincrement": false
        },
        "qr_code_base64": {
          "name": "qr_code_base64",
          "type": "text",
          "primaryKey": false,
          "notNull": false,
          "autoincrement": false
        }
      },
      "indexes": {},
      "foreignKeys": {
        "transactions_created_by_users_id_fk": {
          "name": "transactions_created_by_users_id_fk",
          "tableFrom": "transactions",
          "tableTo": "users",
          "columnsFrom": [
            "created_by"
          ],
          "columnsTo": [
            "id"
          ],
          "onDelete": "no action",
          "onUpdate": "no action"
        },
        "transactions_target_ulp_id_ulps_id_fk": {
          "name": "transactions_target_ulp_id_ulps_id_fk",
          "tableFrom": "transactions",
          "tableTo": "ulps",
          "columnsFrom": [
            "target_ulp_id"
          ],
          "columnsTo": [
            "id"
          ],
          "onDelete": "no action",
          "onUpdate": "no action"
        }
      },
      "compositePrimaryKeys": {
        "transactions_id": {
          "name": "transactions_id",
          "columns": [
            "id"
          ]
        }
      },
      "uniqueConstraints": {
        "transactions_reference_number_unique": {
          "name": "transactions_reference_number_unique",
          "columns": [
            "reference_number"
          ]
        }
      },
      "checkConstraint": {}
    },
    "ulps": {
      "name": "ulps",
      "columns": {
        "id": {
          "name": "id",
          "type": "int",
          "primaryKey": false,
          "notNull": true,
          "autoincrement": true
        },
        "name": {
          "name": "name",
          "type": "varchar(100)",
          "primaryKey": false,
          "notNull": true,
          "autoincrement": false
        }
      },
      "indexes": {},
      "foreignKeys": {},
      "compositePrimaryKeys": {
        "ulps_id": {
          "name": "ulps_id",
          "columns": [
            "id"
          ]
        }
      },
      "uniqueConstraints": {},
      "checkConstraint": {}
    },
    "users": {
      "name": "users",
      "columns": {
        "id": {
          "name": "id",
          "type": "int",
          "primaryKey": false,
          "notNull": true,
          "autoincrement": true
        },
        "username": {
          "name": "username",
          "type": "varchar(50)",
          "primaryKey": false,
          "notNull": true,
          "autoincrement": false
        },
        "password_hash": {
          "name": "password_hash",
          "type": "varchar(255)",
          "primaryKey": false,
          "notNull": true,
          "autoincrement": false
        },
        "role": {
          "name": "role",
          "type": "enum('ADMIN_UP3','ADMIN_ULP')",
          "primaryKey": false,
          "notNull": true,
          "autoincrement": false
        },
        "ulp_id": {
          "name": "ulp_id",
          "type": "int",
          "primaryKey": false,
          "notNull": false,
          "autoincrement": false
        }
      },
      "indexes": {},
      "foreignKeys": {
        "users_ulp_id_ulps_id_fk": {
          "name": "users_ulp_id_ulps_id_fk",
          "tableFrom": "users",
          "tableTo": "ulps",
          "columnsFrom": [
            "ulp_id"
          ],
          "columnsTo": [
            "id"
          ],
          "onDelete": "no action",
          "onUpdate": "no action"
        }
      },
      "compositePrimaryKeys": {
        "users_id": {
          "name": "users_id",
          "columns": [
            "id"
          ]
        }
      },
      "uniqueConstraints": {
        "users_username_unique": {
          "name": "users_username_unique",
          "columns": [
            "username"
          ]
        }
      },
      "checkConstraint": {}
    }
  },
  "views": {},
  "_meta": {
    "schemas": {},
    "tables": {},
    "columns": {}
  },
  "internal": {
    "tables": {},
    "indexes": {}
  }
}